ds_toolkit/__init__.py
ds_toolkit/arrays.py
ds_toolkit/bplist.py
ds_toolkit/files.py
ds_toolkit/internet.py
ds_toolkit/json_helpers.py
ds_toolkit/logger.py
ds_toolkit/progress_bar.py
ds_toolkit/text.py
ds_toolkit/time.py
ds_toolkit/zip.py
ds_toolkit-0.1.2.dist-info/LICENSE
ds_toolkit-0.1.2.dist-info/WHEEL
ds_toolkit-0.1.2.dist-info/METADATA
ds_toolkit-0.1.2.dist-info/RECORD
