Metadata-Version: 2.1
Name: ds-toolkit
Version: 0.1.2
Summary: A toolkit full of random & helpful abilities
Home-page: https://gitlab.com/davidsilva2841/ds-toolkit
License: MIT
Author: David Silva
Author-email: davidsilva2841+gitlab@gmail.com
Requires-Python: >=3.8,<4.0
Classifier: License :: OSI Approved :: MIT License
Classifier: Programming Language :: Python :: 3
Classifier: Programming Language :: Python :: 3.8
Classifier: Programming Language :: Python :: 3.9
Classifier: Topic :: Text Processing :: General
Classifier: Topic :: Utilities
Requires-Dist: PyPrind (>=2.11.3,<3.0.0)
Requires-Dist: bs4 (>=0.0.1,<0.0.2)
Requires-Dist: python-magic (>=0.4.24,<0.5.0)
Requires-Dist: requests (>=2.26.0,<3.0.0)
Project-URL: Repository, https://gitlab.com/davidsilva2841/ds-toolkit
